audio_toolkit
